brubeckservice
