Metadata-Version: 1.0
Name: brubeck-service
Version: 0.1.4
Summary: Library to allow Brubeck framework to call other instances as services
Home-page: http://github.com/sethmurphy/brubeckservices
Author: Seth Murphy
Author-email: seth@brooklyncode.com
License: UNKNOWN
Platform: UNKNOWN
